HuancaihuashengQuantuiWenji202005/README.md
HuancaihuashengQuantuiWenji202005/__init__.py
HuancaihuashengQuantuiWenji202005/__main__.py
HuancaihuashengQuantuiWenji202005/file.epub
HuancaihuashengQuantuiWenji202005/index.html
HuancaihuashengQuantuiWenji202005/css/__init__.py
HuancaihuashengQuantuiWenji202005/css/annotations.css
HuancaihuashengQuantuiWenji202005/css/main.css
HuancaihuashengQuantuiWenji202005/css/normalize.css
HuancaihuashengQuantuiWenji202005/css/popup.css
HuancaihuashengQuantuiWenji202005/font/__init__.py
HuancaihuashengQuantuiWenji202005/font/fontello.eot
HuancaihuashengQuantuiWenji202005/font/fontello.svg
HuancaihuashengQuantuiWenji202005/font/fontello.ttf
HuancaihuashengQuantuiWenji202005/font/fontello.woff
HuancaihuashengQuantuiWenji202005/img/__init__.py
HuancaihuashengQuantuiWenji202005/img/annotator-glyph-sprite.png
HuancaihuashengQuantuiWenji202005/img/annotator-icon-sprite.png
HuancaihuashengQuantuiWenji202005/img/apple-touch-icon.png
HuancaihuashengQuantuiWenji202005/img/cancelfullscreen.png
HuancaihuashengQuantuiWenji202005/img/close.png
HuancaihuashengQuantuiWenji202005/img/fullscreen.png
HuancaihuashengQuantuiWenji202005/img/loader.gif
HuancaihuashengQuantuiWenji202005/img/menu-icon.png
HuancaihuashengQuantuiWenji202005/img/save.png
HuancaihuashengQuantuiWenji202005/img/saved.png
HuancaihuashengQuantuiWenji202005/img/settings-s.png
HuancaihuashengQuantuiWenji202005/img/settings.png
HuancaihuashengQuantuiWenji202005/img/star.png
HuancaihuashengQuantuiWenji202005/js/__init__.py
HuancaihuashengQuantuiWenji202005/js/epub.js
HuancaihuashengQuantuiWenji202005/js/epub.min.js
HuancaihuashengQuantuiWenji202005/js/epub.min.map
HuancaihuashengQuantuiWenji202005/js/hooks.min.js
HuancaihuashengQuantuiWenji202005/js/hooks.min.map
HuancaihuashengQuantuiWenji202005/js/reader.js
HuancaihuashengQuantuiWenji202005/js/reader.js.map
HuancaihuashengQuantuiWenji202005/js/reader.min.js
HuancaihuashengQuantuiWenji202005/js/reader.min.map
huancaihuasheng_quantui_wenji_202005-2022.10.10.0.dist-info/METADATA
huancaihuasheng_quantui_wenji_202005-2022.10.10.0.dist-info/WHEEL
huancaihuasheng_quantui_wenji_202005-2022.10.10.0.dist-info/entry_points.txt
huancaihuasheng_quantui_wenji_202005-2022.10.10.0.dist-info/top_level.txt
huancaihuasheng_quantui_wenji_202005-2022.10.10.0.dist-info/RECORD
